embed-templator/__init__.py
embed_templator/__init__.py
embed_templator/embed_templator.py
embed_templator/exceptions.py
embed_templator-1.0.4.dist-info/LICENSE
embed_templator-1.0.4.dist-info/METADATA
embed_templator-1.0.4.dist-info/WHEEL
embed_templator-1.0.4.dist-info/top_level.txt
embed_templator-1.0.4.dist-info/RECORD
