Metadata-Version: 2.1
Name: embed-templator
Version: 1.0.4
Summary: A Python Template manager for your discord bot to keep your embeds simple & consistent. 
Home-page: https://github.com/Sigmanificient/Embed-Templator
Author: Sigmanificient
Author-email: edhyjox@gmail.com
License: MIT
Platform: UNKNOWN
Classifier: License :: OSI Approved :: MIT License
Classifier: Programming Language :: Python :: 3.6
Classifier: Programming Language :: Python :: 3.7
Classifier: Programming Language :: Python :: 3.8
License-File: LICENSE
Requires-Dist: discord.py
